README.md
setup.py
floor/__init__.py
floor/floor.py
floor.egg-info/PKG-INFO
floor.egg-info/SOURCES.txt
floor.egg-info/dependency_links.txt
floor.egg-info/top_level.txt