Metadata-Version: 1.0
Name: floor
Version: 0.0.1
Summary: a python module to floor strings or variables
Home-page: UNKNOWN
Author: Shayan B.
Author-email: sebebse9554@gmail.com
License: UNKNOWN
Platform: UNKNOWN
